fss_utils/__init__.py
fss_utils/http_errors.py
fss_utils/jwt_manager.py
fss_utils/jwt_validate.py
fss_utils/sshkey.py
fss_utils/vouch_encoder.py
fabric_fss_utils-1.6.1.dist-info/licenses/LICENSE
fabric_fss_utils-1.6.1.dist-info/WHEEL
fabric_fss_utils-1.6.1.dist-info/METADATA
fabric_fss_utils-1.6.1.dist-info/RECORD
