Metadata-Version: 2.4
Name: fabric_fss_utils
Version: 1.6.1
Summary: FABRIC System Service Utilities - JWT and SSH key handling
Author-email: Komal Thareja <kthare10@renci.org>
Requires-Python: >=3.9
Classifier: License :: OSI Approved :: MIT License
Classifier: Programming Language :: Python :: 3
Classifier: Operating System :: OS Independent
License-File: LICENSE
Requires-Dist: cryptography
Requires-Dist: PyJWT
Requires-Dist: Flask
Requires-Dist: Authlib
Requires-Dist: requests
Requires-Dist: pytest ; extra == "test"
Project-URL: Home, https://github.com/fabric-testbed/system-service-utils
Provides-Extra: test
